strutil.py
strutil-0.2.1.dist-info/DESCRIPTION.rst
strutil-0.2.1.dist-info/METADATA
strutil-0.2.1.dist-info/RECORD
strutil-0.2.1.dist-info/WHEEL
strutil-0.2.1.dist-info/metadata.json
strutil-0.2.1.dist-info/top_level.txt
