Metadata-Version: 1.1
Name: strutil
Version: 0.2.1
Summary: Simple tools for downloading, cleaning, extracting and parsing content
Home-page: https://github.com/dakrauth/strutil
Author: David A Krauth
Author-email: dakrauth@gmail.com
License: MIT License
Platform: any
Classifier: Development Status :: 4 - Beta
Classifier: License :: OSI Approved :: MIT License
Classifier: Programming Language :: Python
Classifier: Programming Language :: Python :: 3
Classifier: Programming Language :: Python :: 3.4
Classifier: Programming Language :: Python :: 3.5
Classifier: Programming Language :: Python :: 3.6
Classifier: Topic :: Software Development :: Libraries :: Python Modules
Classifier: Topic :: Text Processing
